{
  "centreId": "cheltenham",
  "centreName": "Cheltenham Driving Test Centre",
  "address": "Driver and Vehicle Standards Agency, Driving Test Centre Cheltenham, Bishopsgate House, 94 All Saints Road, Cheltenham",
  "postcode": "GL52 2HQ",
  "routeCount": 31,
  "allRoads": [
    "Albemarle Gate",
    "Albert Road",
    "Albion Street",
    "All Saints' Road",
    "Alstone Avenue",
    "Alstone Lane",
    "Ambrose Street",
    "Andover Road",
    "Arle Road",
    "Athelney Way",
    "Bafford Approach",
    "Baker Street",
    "Bath Parade",
    "Bath Road",
    "Berkeley Street",
    "Boulton Road",
    "Bouncers Lane",
    "Bowbridge Lane",
    "Bramley Road",
    "Brymore Avenue",
    "Burton Street",
    "Caernarvon Road",
    "Cakebridge Road",
    "Carlton Street",
    "Central Cross Drive",
    "Charlton Lane",
    "Cheltenham Road",
    "Chiltern Road",
    "Church Road",
    "Churchill Drive",
    "Cirencester Road",
    "Clarence Road",
    "Clarence Square",
    "Clarence Street",
    "Clarington Mews",
    "Cleeve View Road",
    "Cleeveland Street",
    "Cleevemount Road",
    "College Baths Road",
    "College Road",
    "Copt Elm Road",
    "Cranham Road",
    "Cromwell Road",
    "Crown Drive",
    "Dale Walk",
    "Dark Lane",
    "Deep Street",
    "Duke Street",
    "Dunalley Street",
    "Eldon Road",
    "Ellenborough Road",
    "Elm Street",
    "Evesham Road",
    "Fairview Road",
    "Fairview Street",
    "Folly Lane",
    "Glenfall Street",
    "Gloucester Place",
    "Gloucester Road",
    "Greenhills Road",
    "Hales Road",
    "Hall Road",
    "Hanover Street",
    "Hatherley Lane",
    "Hatherley Road",
    "Haywards Road",
    "Henrietta Street",
    "Hewlett Road",
    "High Street",
    "Hill Court Road",
    "Hilltop Road",
    "Hyde Lane",
    "Imperial Circus",
    "Imperial Square",
    "Kayte Lane",
    "Keynsham Road",
    "King Alfred Way",
    "Kings Road",
    "Kingsditch Lane",
    "Knapp Road",
    "Lansdown Road",
    "Larput Place",
    "Leckhampton Road",
    "Linden Avenue",
    "London Road",
    "Lyefield Road West",
    "Malden Road",
    "Mandarin Way",
    "Mill Street",
    "Millhouse Drive",
    "Monson Avenue",
    "Montpellier Drive",
    "Montpellier Terrace",
    "Moorend Grove",
    "Moorend Park Road",
    "Moorend Road",
    "Naunton Lane",
    "Naunton Park Road",
    "New Barn Avenue",
    "New Barn Close",
    "New Barn Lane",
    "New Road",
    "New Street",
    "North Place",
    "Old Bath Road",
    "Old Road",
    "Orchard Avenue",
    "Orchard Way",
    "Oriel Road",
    "Pagets Road",
    "Park Place",
    "Pittville Circus",
    "Pittville Circus Road",
    "Pittville Lawn",
    "Pittville Street",
    "Poole Way",
    "Portland Street",
    "Prestbury Road",
    "Princes Street",
    "Princess Elizabeth Way",
    "Priors Road",
    "Priory Street",
    "Quat Goose Lane",
    "Queen Street",
    "Queen's Road",
    "Rivelands Road",
    "Roman Hackle Avenue",
    "Royal Well Road",
    "Russell Street",
    "Saint George's Street",
    "Saint Georges Road",
    "Saint James Square",
    "Saint James Street",
    "Saint Margaret's Road",
    "Saint Paul's Road",
    "Saint Pauls Street North",
    "Sandford Mill Road",
    "Sandford Road",
    "Saxon Way",
    "Selkirk Street",
    "Seneca Way",
    "Severn Road",
    "Shaw Green Lane",
    "Shurdington Road",
    "Southam Lane",
    "Southam Road",
    "St Paul's Road",
    "Stantons Drive",
    "Suffolk Square",
    "Sun Street",
    "Swindon Lane",
    "Swindon Road",
    "Sydenham Road North",
    "Tanners Road",
    "Tatchley Lane",
    "Tewkesbury Road",
    "The Bank",
    "The Burgage",
    "The Park",
    "Thirlestaine Road",
    "Thornton Mews",
    "Tommy Taylors Lane",
    "Townsend Street",
    "Trafalgar Street",
    "Two Hedges Road",
    "Up Hatherley Way",
    "Victoria Place",
    "Victoria Street",
    "Waterloo Street",
    "Welland Drive",
    "Welland Lodge Road",
    "Wellesley Road",
    "Wellington Road",
    "Wellington Square",
    "West Drive",
    "Whaddon Avenue",
    "Whaddon Road",
    "Winchcombe Street",
    "Windyridge Road",
    "Winstonian Road",
    "Wymans Lane"
  ],
  "routes": [
    {
      "routeNumber": 1,
      "distanceKm": 9.5,
      "durationMins": 23,
      "keyRoads": [
        "Albert Road",
        "All Saints' Road",
        "Central Cross Drive",
        "Church Road",
        "Clarence Road",
        "Dark Lane",
        "Evesham Road",
        "Henrietta Street",
        "High Street",
        "Hyde Lane",
        "Kingsditch Lane",
        "North Place",
        "Pittville Circus",
        "Pittville Circus Road",
        "Pittville Lawn",
        "Quat Goose Lane",
        "Rivelands Road",
        "Saint Margaret's Road",
        "Stantons Drive",
        "Wellington Road"
      ],
      "roundabouts": 6,
      "turns": 17
    },
    {
      "routeNumber": 2,
      "distanceKm": 14.6,
      "durationMins": 38,
      "keyRoads": [
        "Albert Road",
        "Albion Street",
        "Central Cross Drive",
        "Clarence Road",
        "Clarence Street",
        "Dark Lane",
        "Evesham Road",
        "Fairview Road",
        "High Street",
        "Imperial Circus",
        "Kingsditch Lane",
        "Malden Road",
        "North Place",
        "Pittville Street",
        "Poole Way",
        "Prestbury Road",
        "Quat Goose Lane",
        "Saint Margaret's Road",
        "Stantons Drive",
        "Wellington Road",
        "West Drive",
        "Winchcombe Street"
      ],
      "roundabouts": 5,
      "turns": 19
    },
    {
      "routeNumber": 3,
      "distanceKm": 13.4,
      "durationMins": 30,
      "keyRoads": [
        "Albion Street",
        "Clarence Road",
        "Clarence Street",
        "Fairview Road",
        "Folly Lane",
        "High Street",
        "Hilltop Road",
        "Hyde Lane",
        "Imperial Circus",
        "North Place",
        "Pittville Street",
        "Prestbury Road",
        "Saint Paul's Road",
        "Swindon Lane",
        "Tewkesbury Road",
        "Tommy Taylors Lane",
        "Townsend Street",
        "Wellington Road",
        "Winchcombe Street"
      ],
      "roundabouts": 5,
      "turns": 15
    },
    {
      "routeNumber": 4,
      "distanceKm": 15,
      "durationMins": 31,
      "keyRoads": [
        "Albion Street",
        "Clarence Street",
        "Evesham Road",
        "Fairview Road",
        "High Street",
        "Imperial Circus",
        "New Barn Avenue",
        "New Barn Close",
        "New Barn Lane",
        "New Road",
        "North Place",
        "Pittville Street",
        "Portland Street",
        "Prestbury Road",
        "Southam Lane",
        "Southam Road",
        "Two Hedges Road",
        "Wellington Road",
        "Winchcombe Street"
      ],
      "roundabouts": 4,
      "turns": 20
    },
    {
      "routeNumber": 5,
      "distanceKm": 15.9,
      "durationMins": 37,
      "keyRoads": [
        "Albert Road",
        "Albion Street",
        "Carlton Street",
        "Central Cross Drive",
        "Clarence Street",
        "Eldon Road",
        "Evesham Road",
        "Fairview Road",
        "Hales Road",
        "Hewlett Road",
        "High Street",
        "Hilltop Road",
        "Imperial Circus",
        "Malden Road",
        "North Place",
        "Old Road",
        "Pittville Street",
        "Prestbury Road",
        "Priors Road",
        "Southam Lane",
        "Southam Road",
        "Swindon Lane",
        "Wellington Road",
        "West Drive",
        "Winchcombe Street"
      ],
      "roundabouts": 7,
      "turns": 26
    },
    {
      "routeNumber": 7,
      "distanceKm": 14.4,
      "durationMins": 33,
      "keyRoads": [
        "Albion Street",
        "Bouncers Lane",
        "Chiltern Road",
        "Clarence Road",
        "Clarence Street",
        "Evesham Road",
        "Fairview Road",
        "Hewlett Road",
        "High Street",
        "Imperial Circus",
        "North Place",
        "Old Road",
        "Pittville Street",
        "Prestbury Road",
        "Priors Road",
        "Southam Lane",
        "Southam Road",
        "St Paul's Road",
        "Swindon Lane"
      ],
      "roundabouts": 3,
      "turns": 17
    },
    {
      "routeNumber": 8,
      "distanceKm": 11.4,
      "durationMins": 25,
      "keyRoads": [
        "Albion Street",
        "Cakebridge Road",
        "Clarence Road",
        "Clarence Street",
        "Cleevemount Road",
        "Evesham Road",
        "Fairview Road",
        "High Street",
        "Imperial Circus",
        "Monson Avenue",
        "North Place",
        "Old Road",
        "Pittville Street",
        "Prestbury Road",
        "Saint Margaret's Road",
        "Welland Lodge Road",
        "Winchcombe Street"
      ],
      "roundabouts": 2,
      "turns": 17
    },
    {
      "routeNumber": 9,
      "distanceKm": 16.5,
      "durationMins": 37,
      "keyRoads": [
        "Albion Street",
        "Clarence Street",
        "Fairview Road",
        "Hewlett Road",
        "High Street",
        "Imperial Circus",
        "North Place",
        "Old Road",
        "Pittville Street",
        "Prestbury Road",
        "Tatchley Lane",
        "Welland Drive",
        "Welland Lodge Road",
        "Whaddon Road"
      ],
      "roundabouts": 3,
      "turns": 12
    },
    {
      "routeNumber": 11,
      "distanceKm": 16,
      "durationMins": 35,
      "keyRoads": [
        "Albert Road",
        "Albion Street",
        "Clarence Road",
        "Clarence Street",
        "Dale Walk",
        "Eldon Road",
        "Ellenborough Road",
        "Fairview Road",
        "Hales Road",
        "High Street",
        "Imperial Circus",
        "Kayte Lane",
        "New Barn Lane",
        "New Road",
        "North Place",
        "Pagets Road",
        "Pittville Street",
        "Prestbury Road",
        "Two Hedges Road"
      ],
      "roundabouts": 4,
      "turns": 18
    },
    {
      "routeNumber": 12,
      "distanceKm": 15.3,
      "durationMins": 37,
      "keyRoads": [
        "Albion Street",
        "Central Cross Drive",
        "Clarence Road",
        "Clarence Street",
        "Evesham Road",
        "Fairview Road",
        "High Street",
        "Hill Court Road",
        "Imperial Circus",
        "New Barn Lane",
        "North Place",
        "Old Road",
        "Pittville Street",
        "Portland Street",
        "Prestbury Road",
        "Southam Lane",
        "Southam Road",
        "Wellington Road",
        "Wellington Square",
        "West Drive",
        "Winchcombe Street"
      ],
      "roundabouts": 5,
      "turns": 30
    },
    {
      "routeNumber": 13,
      "distanceKm": 12.2,
      "durationMins": 34,
      "keyRoads": [
        "Albion Street",
        "Bafford Approach",
        "Cirencester Road",
        "Clarence Street",
        "College Baths Road",
        "Cranham Road",
        "Eldon Road",
        "Greenhills Road",
        "Hales Road",
        "Hewlett Road",
        "High Street",
        "Imperial Circus",
        "Keynsham Road",
        "Kings Road",
        "London Road",
        "Lyefield Road West",
        "Naunton Lane",
        "Naunton Park Road",
        "North Place",
        "Old Bath Road",
        "Pittville Street",
        "Saint James Street",
        "Sydenham Road North",
        "Thirlestaine Road"
      ],
      "roundabouts": 0,
      "turns": 27
    },
    {
      "routeNumber": 14,
      "distanceKm": 12.1,
      "durationMins": 33,
      "keyRoads": [
        "Albion Street",
        "Andover Road",
        "Bath Parade",
        "Clarence Street",
        "Fairview Road",
        "Hall Road",
        "Hewlett Road",
        "High Street",
        "Imperial Circus",
        "Leckhampton Road",
        "London Road",
        "Montpellier Drive",
        "Moorend Grove",
        "Moorend Park Road",
        "Moorend Road",
        "North Place",
        "Pittville Street",
        "The Park"
      ],
      "roundabouts": 2,
      "turns": 19
    },
    {
      "routeNumber": 15,
      "distanceKm": 13.8,
      "durationMins": 32,
      "keyRoads": [
        "Albert Road",
        "Albion Street",
        "Clarence Road",
        "Clarence Street",
        "Fairview Road",
        "High Street",
        "Hill Court Road",
        "Hyde Lane",
        "Imperial Circus",
        "Millhouse Drive",
        "New Barn Lane",
        "North Place",
        "Pittville Circus",
        "Pittville Street",
        "Prestbury Road",
        "Roman Hackle Avenue",
        "Swindon Lane",
        "Wellington Road",
        "Winchcombe Street",
        "Windyridge Road"
      ],
      "roundabouts": 7,
      "turns": 18
    },
    {
      "routeNumber": 16,
      "distanceKm": 15.6,
      "durationMins": 33,
      "keyRoads": [
        "All Saints' Road",
        "Bouncers Lane",
        "Carlton Street",
        "Clarence Road",
        "Cleeve View Road",
        "Deep Street",
        "Evesham Road",
        "Hales Road",
        "Hewlett Road",
        "Kingsditch Lane",
        "Old Road",
        "Pittville Circus",
        "Pittville Circus Road",
        "Prestbury Road",
        "Priors Road",
        "Saint Paul's Road",
        "Southam Lane",
        "Southam Road",
        "Swindon Lane",
        "Swindon Road",
        "Tewkesbury Road",
        "Waterloo Street",
        "Whaddon Road",
        "Windyridge Road"
      ],
      "roundabouts": 6,
      "turns": 16
    },
    {
      "routeNumber": 17,
      "distanceKm": 13.8,
      "durationMins": 31,
      "keyRoads": [
        "All Saints' Road",
        "Cleevemount Road",
        "Cromwell Road",
        "Fairview Road",
        "Hyde Lane",
        "New Barn Lane",
        "Pittville Circus",
        "Pittville Circus Road",
        "Prestbury Road",
        "Saint Pauls Street North",
        "Severn Road",
        "St Paul's Road",
        "Swindon Road",
        "Victoria Place",
        "Welland Lodge Road",
        "Whaddon Road",
        "Winstonian Road",
        "Wymans Lane"
      ],
      "roundabouts": 3,
      "turns": 20
    },
    {
      "routeNumber": 18,
      "distanceKm": 11.9,
      "durationMins": 30,
      "keyRoads": [
        "Albion Street",
        "All Saints' Road",
        "Berkeley Street",
        "Clarence Road",
        "Clarence Street",
        "Cleevemount Road",
        "Cromwell Road",
        "Hewlett Road",
        "High Street",
        "Monson Avenue",
        "New Barn Lane",
        "Oriel Road",
        "Pittville Circus",
        "Pittville Circus Road",
        "Prestbury Road",
        "Royal Well Road",
        "Saint Georges Road",
        "Saint Paul's Road",
        "Severn Road",
        "Swindon Lane",
        "Swindon Road",
        "Welland Lodge Road",
        "Whaddon Road",
        "Windyridge Road"
      ],
      "roundabouts": 3,
      "turns": 16
    },
    {
      "routeNumber": 19,
      "distanceKm": 14.5,
      "durationMins": 32,
      "keyRoads": [
        "All Saints' Road",
        "Ambrose Street",
        "Burton Street",
        "Clarence Road",
        "Evesham Road",
        "Fairview Road",
        "Henrietta Street",
        "High Street",
        "Kingsditch Lane",
        "Knapp Road",
        "New Street",
        "Old Road",
        "Pittville Circus",
        "Pittville Circus Road",
        "Saint James Square",
        "Southam Lane",
        "Swindon Lane",
        "Wellington Road"
      ],
      "roundabouts": 6,
      "turns": 15
    },
    {
      "routeNumber": 20,
      "distanceKm": 14.5,
      "durationMins": 37,
      "keyRoads": [
        "All Saints' Road",
        "Bath Road",
        "Caernarvon Road",
        "Fairview Road",
        "Fairview Street",
        "Glenfall Street",
        "Gloucester Road",
        "Hatherley Lane",
        "Hatherley Road",
        "Hewlett Road",
        "Princess Elizabeth Way",
        "Sandford Road",
        "Selkirk Street",
        "Shurdington Road",
        "Up Hatherley Way"
      ],
      "roundabouts": 12,
      "turns": 9
    },
    {
      "routeNumber": 21,
      "distanceKm": 14.7,
      "durationMins": 31,
      "keyRoads": [
        "Albemarle Gate",
        "All Saints' Road",
        "Boulton Road",
        "Bowbridge Lane",
        "Carlton Street",
        "Cromwell Road",
        "Evesham Road",
        "Hales Road",
        "Hewlett Road",
        "Old Road",
        "Pittville Circus Road",
        "Prestbury Road",
        "Priors Road",
        "Severn Road",
        "Shaw Green Lane",
        "Southam Lane",
        "Swindon Lane",
        "Tatchley Lane",
        "The Burgage",
        "Tommy Taylors Lane",
        "Wellington Road"
      ],
      "roundabouts": 3,
      "turns": 19
    },
    {
      "routeNumber": 22,
      "distanceKm": 9.4,
      "durationMins": 27,
      "keyRoads": [
        "All Saints' Road",
        "Clarence Road",
        "Clarence Square",
        "Clarington Mews",
        "Evesham Road",
        "Fairview Road",
        "Hanover Street",
        "Henrietta Street",
        "Hewlett Road",
        "High Street",
        "Larput Place",
        "North Place",
        "Pittville Circus",
        "Pittville Circus Road",
        "Saint George's Street",
        "Saint Margaret's Road",
        "St Paul's Road",
        "Swindon Lane",
        "Swindon Road",
        "Thornton Mews",
        "Tommy Taylors Lane",
        "Victoria Street",
        "Wellesley Road",
        "Wellington Road",
        "Wymans Lane"
      ],
      "roundabouts": 2,
      "turns": 21
    },
    {
      "routeNumber": 23,
      "distanceKm": 14.4,
      "durationMins": 29,
      "keyRoads": [
        "Albert Road",
        "All Saints' Road",
        "Brymore Avenue",
        "Central Cross Drive",
        "Evesham Road",
        "Hill Court Road",
        "Kayte Lane",
        "Linden Avenue",
        "New Barn Lane",
        "New Road",
        "Pittville Circus",
        "Pittville Circus Road",
        "Pittville Lawn",
        "Southam Lane",
        "Southam Road",
        "Tatchley Lane",
        "The Burgage",
        "Two Hedges Road",
        "Wellington Road"
      ],
      "roundabouts": 6,
      "turns": 16
    },
    {
      "routeNumber": 24,
      "distanceKm": 12.4,
      "durationMins": 31,
      "keyRoads": [
        "All Saints' Road",
        "Bouncers Lane",
        "Brymore Avenue",
        "Carlton Street",
        "Clarence Road",
        "Deep Street",
        "Eldon Road",
        "Hales Road",
        "Hewlett Road",
        "High Street",
        "Linden Avenue",
        "Mill Street",
        "New Barn Lane",
        "Pittville Circus",
        "Pittville Circus Road",
        "Prestbury Road",
        "Priors Road",
        "Queen Street",
        "Saint Paul's Road",
        "Sun Street",
        "Swindon Lane",
        "Swindon Road",
        "Tewkesbury Road",
        "The Bank",
        "The Burgage",
        "Wymans Lane"
      ],
      "roundabouts": 5,
      "turns": 16
    },
    {
      "routeNumber": 25,
      "distanceKm": 10.4,
      "durationMins": 28,
      "keyRoads": [
        "Albert Road",
        "All Saints' Road",
        "Carlton Street",
        "Central Cross Drive",
        "Clarence Road",
        "Clarence Street",
        "College Road",
        "Duke Street",
        "Gloucester Road",
        "Hewlett Road",
        "Imperial Square",
        "Lansdown Road",
        "London Road",
        "Malden Road",
        "Old Bath Road",
        "Oriel Road",
        "Pittville Circus",
        "Pittville Circus Road",
        "Prestbury Road",
        "Princes Street",
        "Priory Street",
        "Queen's Road",
        "Royal Well Road",
        "Sandford Road",
        "Thirlestaine Road",
        "Trafalgar Street",
        "Wellington Road"
      ],
      "roundabouts": 5,
      "turns": 20
    },
    {
      "routeNumber": 26,
      "distanceKm": 9.3,
      "durationMins": 24,
      "keyRoads": [
        "Albion Street",
        "All Saints' Road",
        "Baker Street",
        "Clarence Road",
        "Cleeveland Street",
        "Dunalley Street",
        "Evesham Road",
        "Fairview Road",
        "Gloucester Place",
        "Hewlett Road",
        "High Street",
        "Monson Avenue",
        "North Place",
        "Pittville Circus",
        "Pittville Circus Road",
        "Portland Street",
        "Russell Street",
        "Saint George's Street",
        "Saint Paul's Road",
        "Swindon Lane",
        "Swindon Road",
        "Wellington Road",
        "Wymans Lane"
      ],
      "roundabouts": 3,
      "turns": 22
    },
    {
      "routeNumber": 27,
      "distanceKm": 12.6,
      "durationMins": 32,
      "keyRoads": [
        "All Saints' Road",
        "Bouncers Lane",
        "Brymore Avenue",
        "Clarence Road",
        "Deep Street",
        "Duke Street",
        "Eldon Road",
        "Hales Road",
        "Hewlett Road",
        "High Street",
        "Linden Avenue",
        "Mill Street",
        "New Barn Lane",
        "Pittville Circus",
        "Pittville Circus Road",
        "Prestbury Road",
        "Princes Street",
        "Priors Road",
        "Queen Street",
        "Saint Paul's Road",
        "Sun Street",
        "Swindon Lane",
        "Swindon Road",
        "Sydenham Road North",
        "Tewkesbury Road",
        "The Bank",
        "The Burgage",
        "Whaddon Avenue",
        "Whaddon Road",
        "Wymans Lane"
      ],
      "roundabouts": 5,
      "turns": 20
    },
    {
      "routeNumber": 28,
      "distanceKm": 12.7,
      "durationMins": 34,
      "keyRoads": [
        "Albion Street",
        "All Saints' Road",
        "Bramley Road",
        "Clarence Road",
        "Elm Street",
        "Fairview Road",
        "Keynsham Road",
        "Lansdown Road",
        "London Road",
        "Orchard Avenue",
        "Orchard Way",
        "Pittville Circus",
        "Pittville Circus Road",
        "Prestbury Road",
        "Princess Elizabeth Way",
        "Saint Paul's Road",
        "Swindon Road",
        "Tanners Road",
        "Tewkesbury Road",
        "Thirlestaine Road",
        "Victoria Place",
        "Winchcombe Street",
        "Winstonian Road"
      ],
      "roundabouts": 5,
      "turns": 16
    },
    {
      "routeNumber": 29,
      "distanceKm": 12.9,
      "durationMins": 32,
      "keyRoads": [
        "Albert Road",
        "Albion Street",
        "All Saints' Road",
        "Alstone Avenue",
        "Alstone Lane",
        "Arle Road",
        "Central Cross Drive",
        "Clarence Street",
        "Cleeveland Street",
        "Evesham Road",
        "Gloucester Road",
        "Hewlett Road",
        "Pittville Circus",
        "Pittville Circus Road",
        "Pittville Lawn",
        "Princess Elizabeth Way",
        "Royal Well Road",
        "Saint Georges Road",
        "Saint Paul's Road",
        "Swindon Lane",
        "Swindon Road",
        "Tewkesbury Road",
        "Tommy Taylors Lane",
        "Wellington Road"
      ],
      "roundabouts": 6,
      "turns": 17
    },
    {
      "routeNumber": 30,
      "distanceKm": 8.3,
      "durationMins": 23,
      "keyRoads": [
        "Albion Street",
        "All Saints' Road",
        "Bath Road",
        "Carlton Street",
        "Churchill Drive",
        "Cirencester Road",
        "College Road",
        "Copt Elm Road",
        "Haywards Road",
        "Hewlett Road",
        "King Alfred Way",
        "London Road",
        "Lyefield Road West",
        "Old Bath Road",
        "Pittville Circus Road",
        "Saint James Street",
        "Sandford Mill Road",
        "Sandford Road",
        "Saxon Way",
        "Thirlestaine Road"
      ],
      "roundabouts": 0,
      "turns": 19
    },
    {
      "routeNumber": 31,
      "distanceKm": 13.6,
      "durationMins": 27,
      "keyRoads": [
        "Albert Road",
        "All Saints' Road",
        "Cheltenham Road",
        "Crown Drive",
        "Evesham Road",
        "Hill Court Road",
        "Hyde Lane",
        "Kayte Lane",
        "New Barn Lane",
        "Pittville Circus",
        "Pittville Circus Road",
        "Southam Lane",
        "Swindon Lane",
        "Two Hedges Road",
        "Wellington Road",
        "Wymans Lane"
      ],
      "roundabouts": 7,
      "turns": 11
    },
    {
      "routeNumber": 32,
      "distanceKm": 16,
      "durationMins": 32,
      "keyRoads": [
        "All Saints' Road",
        "Cheltenham Road",
        "Fairview Road",
        "High Street",
        "Hyde Lane",
        "Kayte Lane",
        "Mandarin Way",
        "Old Road",
        "Pittville Circus",
        "Pittville Circus Road",
        "Portland Street",
        "Seneca Way",
        "Southam Lane",
        "Swindon Lane",
        "Two Hedges Road",
        "Windyridge Road",
        "Wymans Lane"
      ],
      "roundabouts": 4,
      "turns": 12
    },
    {
      "routeNumber": 33,
      "distanceKm": 10.4,
      "durationMins": 27,
      "keyRoads": [
        "All Saints' Road",
        "Athelney Way",
        "Bath Road",
        "Charlton Lane",
        "Cirencester Road",
        "College Road",
        "Eldon Road",
        "Greenhills Road",
        "Hales Road",
        "Haywards Road",
        "Hewlett Road",
        "King Alfred Way",
        "Leckhampton Road",
        "Montpellier Terrace",
        "Moorend Park Road",
        "Moorend Road",
        "Old Bath Road",
        "Park Place",
        "Sandford Road",
        "Saxon Way",
        "Shurdington Road",
        "Suffolk Square",
        "The Park"
      ],
      "roundabouts": 3,
      "turns": 13
    }
  ]
}