{
  "centreId": "kings-lynn",
  "centreName": "Kings Lynn Driving Test Centre",
  "address": "Driver and Vehicle Standards Agency, Driving Test Centre Kings Lynn, Rollesby Road, Hardwick Industrial Estate, Kings Lynn",
  "postcode": "PE30 4LS",
  "routeCount": 27,
  "allRoads": [
    "Anthony Nolan Road",
    "Austin Street",
    "Bagge Road",
    "Baldock Drive",
    "Bergen Way",
    "Bishops Road",
    "Blackfriars Road",
    "Blackfriars Street",
    "Bryggen Road",
    "Castle Rising Road",
    "Chase Avenue",
    "Checker Street",
    "Church Lane",
    "Church Street",
    "Clenchwarton Road",
    "Clough Lane",
    "Common Lane",
    "Dawnay Avenue",
    "De Grey Road",
    "Diamond Approach",
    "Diamond Street",
    "Edma Street",
    "Edward Benefer Way",
    "Ethel Terrace",
    "Ferry Road",
    "Ffolkes Drive",
    "Field Lane",
    "Fred Ackland Drive",
    "Friars Street",
    "Gayton Road",
    "Gaywood Road",
    "Gloucester Road",
    "Goodwins Road",
    "Greenyard Way",
    "Grimston Road",
    "Guanock Place",
    "Guanock Terrace",
    "Hall Lane",
    "Hamburg Way",
    "Hansa Road",
    "Hardwick Road",
    "Hextable Road",
    "Hospital Walk",
    "Jermyn Road",
    "John Kennedy Road",
    "Kensington Road",
    "Kent Road",
    "King Street",
    "Lansdowne Street",
    "Loke Road",
    "London Road",
    "Losinga Road",
    "Low Road",
    "Lynn Road",
    "Manor Road",
    "Mill Fleet",
    "Millennium Way",
    "Morston Drift",
    "Nar Ouse Way",
    "Nelson Street",
    "Norfolk Street",
    "North Street",
    "Nursery Lane",
    "Oldmedow Road",
    "Out South Gates",
    "Peppers Green",
    "Pilot Street",
    "Portland Place",
    "Priory Lane",
    "Purfleet Place",
    "Queen Elizabeth Way",
    "Queen Mary Road",
    "Queensway",
    "Raby Avenue",
    "Railway Road",
    "Regent Way",
    "Rollesby Road",
    "Rosebery Avenue",
    "Saddlebow Road",
    "Saint Ann's Street",
    "Saint Edmundsbury Road",
    "Saint James Court",
    "Saint James Street",
    "Saint James' Road",
    "Saint Margaret's Lane",
    "Saint Nicholas Street",
    "Saint Peters Road",
    "Scania Way",
    "Seaman Drive",
    "Sidney Street",
    "South Lynn Plain",
    "South Quay",
    "South Wootton Lane",
    "Southgate Street",
    "Spenser Road",
    "Stonegate Street",
    "Tennyson Avenue",
    "The Friars",
    "Thomas Street",
    "Tower Place",
    "Tuesday Market Place",
    "Valingers Road",
    "Vancouver Avenue",
    "Wellesley Street",
    "Whitefriars Road",
    "William Booth Road",
    "William Street",
    "Windsor Park",
    "Windsor Road",
    "Windsor Terrace",
    "Winston Churchill Drive",
    "Wisbech Road",
    "Wootton Road",
    "York Road"
  ],
  "routes": [
    {
      "routeNumber": 1,
      "distanceKm": 11.3,
      "durationMins": 27,
      "keyRoads": [
        "Church Street",
        "Gaywood Road",
        "Greenyard Way",
        "Hansa Road",
        "Hardwick Road",
        "John Kennedy Road",
        "King Street",
        "Lansdowne Street",
        "Loke Road",
        "Mill Fleet",
        "Nar Ouse Way",
        "North Street",
        "Oldmedow Road",
        "Pilot Street",
        "Priory Lane",
        "Queen Elizabeth Way",
        "Rollesby Road",
        "Saint Ann's Street",
        "Saint Margaret's Lane",
        "Scania Way",
        "South Quay",
        "Tennyson Avenue",
        "Tuesday Market Place"
      ],
      "roundabouts": 9,
      "turns": 21
    },
    {
      "routeNumber": 3,
      "distanceKm": 16.4,
      "durationMins": 34,
      "keyRoads": [
        "Austin Street",
        "Bergen Way",
        "Blackfriars Road",
        "Edward Benefer Way",
        "Goodwins Road",
        "John Kennedy Road",
        "Railway Road",
        "Wellesley Street",
        "Windsor Park",
        "Windsor Road",
        "Windsor Terrace"
      ],
      "roundabouts": 1,
      "turns": 8
    },
    {
      "routeNumber": 5,
      "distanceKm": 16.5,
      "durationMins": 34,
      "keyRoads": [
        "Austin Street",
        "Bergen Way",
        "Edward Benefer Way",
        "Goodwins Road",
        "Hamburg Way",
        "John Kennedy Road",
        "London Road",
        "Railway Road",
        "Wellesley Street",
        "Windsor Road"
      ],
      "roundabouts": 0,
      "turns": 6
    },
    {
      "routeNumber": 6,
      "distanceKm": 18.5,
      "durationMins": 34,
      "keyRoads": [
        "Austin Street",
        "Castle Rising Road",
        "Edward Benefer Way",
        "John Kennedy Road",
        "Loke Road",
        "Manor Road",
        "Nursery Lane",
        "Railway Road",
        "Wellesley Street"
      ],
      "roundabouts": 0,
      "turns": 5
    },
    {
      "routeNumber": 7,
      "distanceKm": 13.6,
      "durationMins": 30,
      "keyRoads": [
        "Austin Street",
        "Bergen Way",
        "Church Lane",
        "Edward Benefer Way",
        "Gayton Road",
        "Gloucester Road",
        "Hall Lane",
        "Hextable Road",
        "Jermyn Road",
        "John Kennedy Road",
        "Lansdowne Street",
        "Loke Road",
        "Low Road",
        "Nursery Lane",
        "Queensway",
        "Railway Road",
        "Rosebery Avenue",
        "Wellesley Street",
        "Wootton Road"
      ],
      "roundabouts": 0,
      "turns": 12
    },
    {
      "routeNumber": 8,
      "distanceKm": 19.6,
      "durationMins": 36,
      "keyRoads": [
        "Austin Street",
        "Bergen Way",
        "Bryggen Road",
        "Dawnay Avenue",
        "Edward Benefer Way",
        "Gloucester Road",
        "Grimston Road",
        "Hamburg Way",
        "Kensington Road",
        "Peppers Green",
        "Queen Elizabeth Way",
        "Railway Road",
        "Rosebery Avenue",
        "South Wootton Lane",
        "Spenser Road",
        "Wellesley Street",
        "Wootton Road"
      ],
      "roundabouts": 3,
      "turns": 12
    },
    {
      "routeNumber": 9,
      "distanceKm": 20.1,
      "durationMins": 36,
      "keyRoads": [
        "Austin Street",
        "Bergen Way",
        "Edward Benefer Way",
        "Gloucester Road",
        "Grimston Road",
        "Hamburg Way",
        "Kensington Road",
        "Loke Road",
        "Queen Elizabeth Way",
        "Railway Road",
        "Rosebery Avenue",
        "Wellesley Street"
      ],
      "roundabouts": 3,
      "turns": 7
    },
    {
      "routeNumber": 10,
      "distanceKm": 13.5,
      "durationMins": 31,
      "keyRoads": [
        "Austin Street",
        "Bagge Road",
        "Edward Benefer Way",
        "London Road",
        "Norfolk Street",
        "Queen Mary Road",
        "Railway Road",
        "Wellesley Street"
      ],
      "roundabouts": 1,
      "turns": 6
    },
    {
      "routeNumber": 11,
      "distanceKm": 14.3,
      "durationMins": 34,
      "keyRoads": [
        "Austin Street",
        "Baldock Drive",
        "Bergen Way",
        "Dawnay Avenue",
        "Edward Benefer Way",
        "Ffolkes Drive",
        "Hamburg Way",
        "London Road",
        "Low Road",
        "Norfolk Street",
        "Peppers Green",
        "Railway Road",
        "South Wootton Lane",
        "Spenser Road",
        "Wellesley Street",
        "Wootton Road"
      ],
      "roundabouts": 1,
      "turns": 15
    },
    {
      "routeNumber": 12,
      "distanceKm": 19,
      "durationMins": 37,
      "keyRoads": [
        "Austin Street",
        "Bergen Way",
        "Edma Street",
        "Edward Benefer Way",
        "Hamburg Way",
        "Low Road",
        "Manor Road",
        "Nursery Lane",
        "Railway Road",
        "Wellesley Street"
      ],
      "roundabouts": 0,
      "turns": 7
    },
    {
      "routeNumber": 14,
      "distanceKm": 15.8,
      "durationMins": 31,
      "keyRoads": [
        "Austin Street",
        "Edward Benefer Way",
        "John Kennedy Road",
        "Loke Road",
        "Railway Road",
        "Wellesley Street"
      ],
      "roundabouts": 1,
      "turns": 2
    },
    {
      "routeNumber": 16,
      "distanceKm": 9.9,
      "durationMins": 24,
      "keyRoads": [
        "Chase Avenue",
        "Diamond Approach",
        "Diamond Street",
        "Friars Street",
        "Greenyard Way",
        "Guanock Place",
        "Hansa Road",
        "Hardwick Road",
        "London Road",
        "Oldmedow Road",
        "Out South Gates",
        "Portland Place",
        "Queen Elizabeth Way",
        "Scania Way",
        "Sidney Street",
        "South Lynn Plain",
        "Southgate Street",
        "Thomas Street",
        "Vancouver Avenue",
        "William Street",
        "Wisbech Road",
        "York Road"
      ],
      "roundabouts": 6,
      "turns": 16
    },
    {
      "routeNumber": 17,
      "distanceKm": 10.6,
      "durationMins": 22,
      "keyRoads": [
        "Clenchwarton Road",
        "Ethel Terrace",
        "Friars Street",
        "Goodwins Road",
        "Guanock Terrace",
        "Hansa Road",
        "Hardwick Road",
        "Hospital Walk",
        "London Road",
        "Oldmedow Road",
        "Out South Gates",
        "Scania Way",
        "Southgate Street",
        "The Friars",
        "Valingers Road",
        "Vancouver Avenue",
        "Whitefriars Road",
        "Wisbech Road",
        "York Road"
      ],
      "roundabouts": 5,
      "turns": 12
    },
    {
      "routeNumber": 18,
      "distanceKm": 14.2,
      "durationMins": 33,
      "keyRoads": [
        "Anthony Nolan Road",
        "Checker Street",
        "Fred Ackland Drive",
        "Friars Street",
        "Gayton Road",
        "Gaywood Road",
        "Greenyard Way",
        "Hardwick Road",
        "John Kennedy Road",
        "Loke Road",
        "London Road",
        "Oldmedow Road",
        "Queen Elizabeth Way",
        "Rollesby Road",
        "Scania Way",
        "Seaman Drive",
        "South Lynn Plain",
        "Winston Churchill Drive"
      ],
      "roundabouts": 6,
      "turns": 10
    },
    {
      "routeNumber": 19,
      "distanceKm": 13.1,
      "durationMins": 30,
      "keyRoads": [
        "Austin Street",
        "Blackfriars Road",
        "Blackfriars Street",
        "Clough Lane",
        "Edward Benefer Way",
        "Gayton Road",
        "Greenyard Way",
        "Hardwick Road",
        "Kensington Road",
        "Kent Road",
        "Loke Road",
        "Lynn Road",
        "Mill Fleet",
        "Oldmedow Road",
        "Queen Elizabeth Way",
        "Queensway",
        "Regent Way",
        "Rollesby Road",
        "Saint James Court",
        "Saint James Street",
        "Saint James' Road",
        "Scania Way",
        "Tower Place",
        "Vancouver Avenue",
        "Windsor Road"
      ],
      "roundabouts": 6,
      "turns": 15
    },
    {
      "routeNumber": 20,
      "distanceKm": 14.3,
      "durationMins": 28,
      "keyRoads": [
        "Clenchwarton Road",
        "Ferry Road",
        "Hansa Road",
        "Hardwick Road",
        "Millennium Way",
        "Morston Drift",
        "Nar Ouse Way",
        "Oldmedow Road",
        "Saint Peters Road",
        "Scania Way",
        "Wisbech Road"
      ],
      "roundabouts": 6,
      "turns": 8
    },
    {
      "routeNumber": 21,
      "distanceKm": 11.6,
      "durationMins": 25,
      "keyRoads": [
        "Gayton Road",
        "Gaywood Road",
        "Greenyard Way",
        "Hardwick Road",
        "Kensington Road",
        "Kent Road",
        "Oldmedow Road",
        "Queen Elizabeth Way",
        "Queensway",
        "Scania Way",
        "Tennyson Avenue",
        "Vancouver Avenue",
        "William Booth Road",
        "Winston Churchill Drive"
      ],
      "roundabouts": 6,
      "turns": 8
    },
    {
      "routeNumber": 22,
      "distanceKm": 13.4,
      "durationMins": 29,
      "keyRoads": [
        "Church Street",
        "Gaywood Road",
        "Greenyard Way",
        "Hansa Road",
        "Hardwick Road",
        "John Kennedy Road",
        "King Street",
        "Loke Road",
        "Mill Fleet",
        "Nar Ouse Way",
        "Nelson Street",
        "North Street",
        "Oldmedow Road",
        "Queen Elizabeth Way",
        "Saint Ann's Street",
        "Saint Margaret's Lane",
        "Scania Way",
        "South Quay",
        "Tennyson Avenue",
        "Tuesday Market Place"
      ],
      "roundabouts": 9,
      "turns": 11
    },
    {
      "routeNumber": 23,
      "distanceKm": 14.4,
      "durationMins": 29,
      "keyRoads": [
        "Clenchwarton Road",
        "Ferry Road",
        "Hansa Road",
        "Hardwick Road",
        "Millennium Way",
        "Morston Drift",
        "Nar Ouse Way",
        "Oldmedow Road",
        "Saddlebow Road",
        "Saint Peters Road",
        "Scania Way",
        "Wisbech Road"
      ],
      "roundabouts": 4,
      "turns": 11
    },
    {
      "routeNumber": 24,
      "distanceKm": 12.8,
      "durationMins": 24,
      "keyRoads": [
        "Clenchwarton Road",
        "Ferry Road",
        "Hansa Road",
        "Hardwick Road",
        "Millennium Way",
        "Oldmedow Road",
        "Saint Peters Road",
        "Scania Way",
        "Wisbech Road"
      ],
      "roundabouts": 4,
      "turns": 5
    },
    {
      "routeNumber": 25,
      "distanceKm": 12.9,
      "durationMins": 29,
      "keyRoads": [
        "Bagge Road",
        "Bishops Road",
        "De Grey Road",
        "Gayton Road",
        "Gaywood Road",
        "Goodwins Road",
        "Greenyard Way",
        "Hansa Road",
        "Hardwick Road",
        "Hospital Walk",
        "Lynn Road",
        "Oldmedow Road",
        "Queen Elizabeth Way",
        "Queen Mary Road",
        "Scania Way",
        "Windsor Terrace"
      ],
      "roundabouts": 6,
      "turns": 11
    },
    {
      "routeNumber": 26,
      "distanceKm": 17.7,
      "durationMins": 30,
      "keyRoads": [
        "Castle Rising Road",
        "Church Lane",
        "Common Lane",
        "Edward Benefer Way",
        "Greenyard Way",
        "Grimston Road",
        "Hall Lane",
        "Hansa Road",
        "Hardwick Road",
        "John Kennedy Road",
        "Nursery Lane",
        "Oldmedow Road",
        "Queen Elizabeth Way",
        "Scania Way"
      ],
      "roundabouts": 7,
      "turns": 6
    },
    {
      "routeNumber": 27,
      "distanceKm": 11.7,
      "durationMins": 23,
      "keyRoads": [
        "Chase Avenue",
        "Clenchwarton Road",
        "Goodwins Road",
        "Hansa Road",
        "Hardwick Road",
        "London Road",
        "Morston Drift",
        "Nar Ouse Way",
        "Oldmedow Road",
        "Saddlebow Road",
        "Scania Way",
        "Vancouver Avenue",
        "Wisbech Road",
        "York Road"
      ],
      "roundabouts": 7,
      "turns": 9
    },
    {
      "routeNumber": 28,
      "distanceKm": 11.1,
      "durationMins": 27,
      "keyRoads": [
        "Austin Street",
        "Blackfriars Road",
        "Edma Street",
        "Edward Benefer Way",
        "Gaywood Road",
        "Hansa Road",
        "Hardwick Road",
        "Loke Road",
        "Losinga Road",
        "Oldmedow Road",
        "Raby Avenue",
        "Saint Edmundsbury Road",
        "Scania Way",
        "Vancouver Avenue"
      ],
      "roundabouts": 3,
      "turns": 9
    },
    {
      "routeNumber": 29,
      "distanceKm": 9.9,
      "durationMins": 26,
      "keyRoads": [
        "Church Street",
        "Edma Street",
        "Edward Benefer Way",
        "Gaywood Road",
        "Hansa Road",
        "Hardwick Road",
        "Loke Road",
        "Mill Fleet",
        "North Street",
        "Oldmedow Road",
        "Purfleet Place",
        "Saint Ann's Street",
        "Saint James' Road",
        "Saint Nicholas Street",
        "Scania Way",
        "Stonegate Street",
        "Tuesday Market Place",
        "Vancouver Avenue"
      ],
      "roundabouts": 3,
      "turns": 13
    },
    {
      "routeNumber": 30,
      "distanceKm": 12.7,
      "durationMins": 29,
      "keyRoads": [
        "Friars Street",
        "Gayton Road",
        "Gaywood Road",
        "Gloucester Road",
        "Goodwins Road",
        "Greenyard Way",
        "Hansa Road",
        "Hardwick Road",
        "Kensington Road",
        "Kent Road",
        "London Road",
        "Oldmedow Road",
        "Out South Gates",
        "Queen Elizabeth Way",
        "Rosebery Avenue",
        "Scania Way",
        "South Lynn Plain",
        "Southgate Street",
        "Windsor Road",
        "Winston Churchill Drive"
      ],
      "roundabouts": 5,
      "turns": 10
    },
    {
      "routeNumber": 31,
      "distanceKm": 15.8,
      "durationMins": 30,
      "keyRoads": [
        "Clenchwarton Road",
        "Field Lane",
        "Gayton Road",
        "Gloucester Road",
        "Greenyard Way",
        "Hansa Road",
        "Hardwick Road",
        "Kensington Road",
        "Nar Ouse Way",
        "Oldmedow Road",
        "Queen Elizabeth Way",
        "Queensway",
        "Rosebery Avenue",
        "Scania Way",
        "Tennyson Avenue",
        "Wisbech Road",
        "Wootton Road"
      ],
      "roundabouts": 10,
      "turns": 9
    }
  ]
}